resolveit/__init__.py
resolveit/app.py
resolveit/cli_output.py
resolveit/fetch_results.py
resolveit/resolveit.py
resolveit/resolveit_types.py
resolveit/rparser.py
resolveit/settings.py
Resolve_IT-1.5.0.dist-info/LICENSE
Resolve_IT-1.5.0.dist-info/METADATA
Resolve_IT-1.5.0.dist-info/WHEEL
Resolve_IT-1.5.0.dist-info/entry_points.txt
Resolve_IT-1.5.0.dist-info/top_level.txt
Resolve_IT-1.5.0.dist-info/RECORD
