Metadata-Version: 2.1
Name: Resolve-IT
Version: 1.5.0
Summary: A CLI tool that fetches Stack Overflow results when an exception is thrown.
Home-page: https://github.com/akshatdalton/Resolve-IT
Author: Akshat
Author-email: akshat.dak@students.iiit.ac.in
License: MIT License
Platform: UNKNOWN
Requires-Python: >=3.5
License-File: LICENSE
Requires-Dist: stackapi
Requires-Dist: requests
Requires-Dist: beautifulsoup4
Requires-Dist: lxml
Requires-Dist: urwid
Requires-Dist: dataclasses
Requires-Dist: colorama
Requires-Dist: pyfiglet
Requires-Dist: clanimate
